setup.py
baeklab/__init__.py
baeklab/cFunction.py
baeklab.egg-info/PKG-INFO
baeklab.egg-info/SOURCES.txt
baeklab.egg-info/dependency_links.txt
baeklab.egg-info/requires.txt
baeklab.egg-info/top_level.txt