Metadata-Version: 1.0
Name: baeklab
Version: 0.0.1
Summary: isoweek calculation and so on
Home-page: http://github.com/kimhyokwan/baeklab
Author: kimhyokwan
Author-email: haiteam@kopo.ac.kr
License: MIT
Keywords: calendar,isoweek,listsum
Platform: UNKNOWN
